{
  "cli": {
    "version": ">= 5.9.1"
  },
  "build": {
    "development": {
      "developmentClient": true,
      "distribution": "internal"
    },
    "preview": {
      "distribution": "internal"
    },
    "testflight": {
      "ios": {
        "buildType": "archive"
      }
    },
    "production": {
      "ios": {
        "buildType": "archive"
      },
      "android": {
        "buildType": "aab"
      }
    }
  },
  "submit": {
    "testflight": {
      "ios": {
        "appleId": "your-apple-id@example.com",
        "ascAppId": "your-app-store-connect-app-id",
        "appleTeamId": "your-apple-team-id"
      }
    },
    "production": {
      "ios": {
        "appleId": "your-apple-id@example.com",
        "ascAppId": "your-app-store-connect-app-id",
        "appleTeamId": "your-apple-team-id"
      },
      "android": {
        "track": "production"
      }
    }
  }
} 